py3dpolys_le/_3dpolys_le.py
py3dpolys_le/_3dpolys_le_runner.py
py3dpolys_le/_3dpolys_le_stats.py
py3dpolys_le/__init__.py
py3dpolys_le/_logging.py
py3dpolys_le/_version.py
py3dpolys_le/hic_analysis.py
py3dpolys_le/hic_converters.py
py3dpolys_le/job_runner.py
py3dpolys_le/plot_hic.py
py3dpolys_le/plot_sim_stats.py
py3dpolys_le/bin/3dpolys_le
py3dpolys_le/bin/cmd.sh
py3dpolys_le-2025.2.dist-info/licenses/LICENSE
py3dpolys_le-2025.2.dist-info/METADATA
py3dpolys_le-2025.2.dist-info/WHEEL
py3dpolys_le-2025.2.dist-info/entry_points.txt
py3dpolys_le-2025.2.dist-info/top_level.txt
py3dpolys_le-2025.2.dist-info/zip-safe
py3dpolys_le-2025.2.dist-info/RECORD
