Metadata-Version: 2.4
Name: py3dpolys_le
Version: 2025.2
Summary: 3D Polymer Simulations - Loop Extrusion model
Home-page: https://gitlab.com/togop/3DPolyS-LE
Author: Daniel Jost, Todor Gitchev
Author-email: Todor Gitchev <todor.gitchev@gmail.com>, Daniel Jost <daniel.jost@ens-lyon.fr>
License: MIT
Project-URL: repository, https://gitlab.com/togop/3DPolyS-LE
Project-URL: Homepage, https://gitlab.com/togop/3DPolyS-LE
Keywords: polymer,chromosome,3D,dynamics,simulations,loop-extrusion
Classifier: Development Status :: 5 - Production/Stable
Classifier: License :: OSI Approved :: MIT License
Classifier: Programming Language :: Fortran
Classifier: Programming Language :: Python :: 3.10
Classifier: Intended Audience :: Science/Research
Classifier: Topic :: Scientific/Engineering :: Bio-Informatics
Classifier: Operating System :: MacOS
Classifier: Operating System :: POSIX :: Linux
Requires-Python: >3.10.0
License-File: LICENSE
Requires-Dist: cooler
Requires-Dist: pyranges
Requires-Dist: numpy
Requires-Dist: pandas
Requires-Dist: matplotlib
Requires-Dist: scipy
Requires-Dist: filelock
Requires-Dist: h5py
Requires-Dist: dask
Requires-Dist: seaborn
Requires-Dist: openmpi>=0.0.0
Requires-Dist: setuptools<81
Provides-Extra: dev
Requires-Dist: pip-tools; extra == "dev"
Requires-Dist: pytest; extra == "dev"
Requires-Dist: pytest-flake8; extra == "dev"
Requires-Dist: pytest-cov; extra == "dev"
Dynamic: author
Dynamic: home-page
Dynamic: license-file
Dynamic: requires-python
